{
  "vanillatweaks:track_stats": {
    "criteria": {
      "tick": "2022-03-19 17:11:43 -0300"
    },
    "done": true
  },
  "vanillatweaks:root": {
    "criteria": {
      "tick": "2022-03-19 17:11:43 -0300"
    },
    "done": true
  },
  "vanillatweaks:track_raw_stats": {
    "criteria": {
      "tick": "2022-03-19 17:11:43 -0300"
    },
    "done": true
  },
  "repurposed_structures:root": {
    "criteria": {
      "always": "2022-03-19 17:11:43 -0300"
    },
    "done": true
  },
  "vanillatweaks:afk_display": {
    "criteria": {
      "tick": "2022-03-19 17:11:43 -0300"
    },
    "done": true
  },
  "blazeandcave:potion/a_much_more_doable_challenge": {
    "criteria": {
      "regeneration": "2022-03-19 17:11:43 -0300",
      "resistance": "2022-03-19 17:11:43 -0300"
    },
    "done": false
  },
  "DataVersion": 2865
}